HISTORY.txt
README.rst
setup.cfg
setup.py
djamqpconsumer/__init__.py
djamqpconsumer/printconsumer.py
djamqpconsumer.egg-info/PKG-INFO
djamqpconsumer.egg-info/SOURCES.txt
djamqpconsumer.egg-info/dependency_links.txt
djamqpconsumer.egg-info/entry_points.txt
djamqpconsumer.egg-info/not-zip-safe
djamqpconsumer.egg-info/requires.txt
djamqpconsumer.egg-info/top_level.txt
djamqpconsumer/management/__init__.py
djamqpconsumer/management/commands/__init__.py
djamqpconsumer/management/commands/consumer.py