Metadata-Version: 1.0
Name: djamqpconsumer
Version: 0.7
Summary: Blocking custom django command to consume a AMQP queue
Home-page: http://github.com/codesyntax/djamqpconsumer
Author: Aitzol Naberan
Author-email: anaberan@gmail.com
License: GPL
Keywords: django amql pika
Platform: UNKNOWN
